clspc/__init__.py
clspc/clspc.py
clspc-1.0.2.dist-info/LICENSE
clspc-1.0.2.dist-info/METADATA
clspc-1.0.2.dist-info/WHEEL
clspc-1.0.2.dist-info/RECORD
