Metadata-Version: 2.1
Name: clspc
Version: 1.0.2
Summary: A Python implementation of closed-loop subspace predictive control
License: MIT
Author: Bert Van den Abbeele
Requires-Python: >=3.10
Classifier: License :: OSI Approved :: MIT License
Classifier: Programming Language :: Python :: 3
Classifier: Programming Language :: Python :: 3.10
Classifier: Programming Language :: Python :: 3.11
Classifier: Programming Language :: Python :: 3.12
Classifier: Programming Language :: Python :: 3.13
Requires-Dist: cvxopt (>=1.3.2)
Requires-Dist: numpy (>=2.1.1)
Requires-Dist: scipy (>=1.14.1)
